odoo/addons/sale_discount_display_amount/README.rst
odoo/addons/sale_discount_display_amount/__init__.py
odoo/addons/sale_discount_display_amount/__manifest__.py
odoo/addons/sale_discount_display_amount/hooks.py
odoo/addons/sale_discount_display_amount/i18n/ca.po
odoo/addons/sale_discount_display_amount/i18n/de.po
odoo/addons/sale_discount_display_amount/i18n/es.po
odoo/addons/sale_discount_display_amount/i18n/es_ES.po
odoo/addons/sale_discount_display_amount/i18n/fr.po
odoo/addons/sale_discount_display_amount/i18n/sale_discount_display_amount.pot
odoo/addons/sale_discount_display_amount/i18n/zh_CN.po
odoo/addons/sale_discount_display_amount/models/__init__.py
odoo/addons/sale_discount_display_amount/models/sale_order.py
odoo/addons/sale_discount_display_amount/models/sale_order_line.py
odoo/addons/sale_discount_display_amount/readme/CONFIGURE.rst
odoo/addons/sale_discount_display_amount/readme/CONTRIBUTORS.rst
odoo/addons/sale_discount_display_amount/readme/DESCRIPTION.rst
odoo/addons/sale_discount_display_amount/readme/USAGE.rst
odoo/addons/sale_discount_display_amount/static/description/icon.png
odoo/addons/sale_discount_display_amount/static/description/index.html
odoo/addons/sale_discount_display_amount/tests/__init__.py
odoo/addons/sale_discount_display_amount/tests/test_discount_display_amount.py
odoo/addons/sale_discount_display_amount/views/sale_view.xml
odoo13_addon_sale_discount_display_amount-13.0.1.0.2.dist-info/METADATA
odoo13_addon_sale_discount_display_amount-13.0.1.0.2.dist-info/WHEEL
odoo13_addon_sale_discount_display_amount-13.0.1.0.2.dist-info/top_level.txt
odoo13_addon_sale_discount_display_amount-13.0.1.0.2.dist-info/RECORD
