Metadata-Version: 2.1
Name: odoo13-addon-sale-discount-display-amount
Version: 13.0.1.0.2
Summary: This addon intends to display the amount of the discount computed on sale_order_line and sale_order level
Home-page: https://github.com/OCA/sale-workflow
Author: ACSONE SA/NV,Odoo Community Association (OCA)
Author-email: support@odoo-community.org
License: AGPL-3
Platform: UNKNOWN
Classifier: Programming Language :: Python
Classifier: Framework :: Odoo
Classifier: License :: OSI Approved :: GNU Affero General Public License v3
Requires-Python: >=3.5
Requires-Dist: odoo (<13.1dev,>=13.0a)
